_polar_lib.abi3.so
oso/__init__.py
oso/__main__.py
oso/oso.py
oso/py.typed
polar/__init__.py
polar/__main__.py
polar/build.py
polar/errors.py
polar/exceptions.py
polar/expression.py
polar/ffi.py
polar/host.py
polar/partial.py
polar/polar.py
polar/predicate.py
polar/py.typed
polar/query.py
polar/variable.py
fiddler-0.11.1.dist-info/METADATA
fiddler-0.11.1.dist-info/WHEEL
fiddler-0.11.1.dist-info/entry_points.txt
fiddler-0.11.1.dist-info/top_level.txt
fiddler-0.11.1.dist-info/RECORD
