Metadata-Version: 2.1
Name: fiddler
Version: 0.11.1
Summary: oso is an open source policy engine for authorization that’s embedded in your application
Home-page: UNKNOWN
Author: Oso Security, Inc.
License: UNKNOWN
Platform: UNKNOWN
Classifier: Development Status :: 4 - Beta
Classifier: Programming Language :: Python :: 3.6
Classifier: License :: OSI Approved :: Apache Software License
Requires-Python: >=3.6
Requires-Dist: cffi ~=1.14
Provides-Extra: django
Provides-Extra: flask
Requires-Dist: flask ; extra == 'flask'
Requires-Dist: authlib ; extra == 'flask'
Provides-Extra: jwt
Requires-Dist: authlib ; extra == 'jwt'
